scrapy_querycleaner/__init__.py
scrapy_querycleaner/middleware.py
scrapy_querycleaner-1.0.0.dist-info/DESCRIPTION.rst
scrapy_querycleaner-1.0.0.dist-info/METADATA
scrapy_querycleaner-1.0.0.dist-info/RECORD
scrapy_querycleaner-1.0.0.dist-info/WHEEL
scrapy_querycleaner-1.0.0.dist-info/metadata.json
scrapy_querycleaner-1.0.0.dist-info/top_level.txt
