Metadata-Version: 2.0
Name: scrapy-querycleaner
Version: 1.0.0
Summary: Scrapy spider middleware to clean up query parameters in request URLs
Home-page: https://github.com/scrapy-plugins/scrapy-querycleaner
Author: Scrapinghub
Author-email: info@scrapinghub.com
License: BSD
Platform: Any
Classifier: Development Status :: 4 - Beta
Classifier: License :: OSI Approved :: BSD License
Classifier: Operating System :: OS Independent
Classifier: Programming Language :: Python
Classifier: Programming Language :: Python :: 2
Classifier: Programming Language :: Python :: 2.7
Classifier: Programming Language :: Python :: 3
Classifier: Programming Language :: Python :: 3.5
Requires-Dist: scrapy (>=1.0)
Requires-Dist: six
